<?xml version="1.0" encoding="utf-8"?>
<!--Copyright, Microsoft Corporation, All rights reserved.-->
<Rule Name="CL" PageTemplate="tool" DisplayName="C/C++" SwitchPrefix="-" Order="10" xmlns="http://schemas.microsoft.com/build/2009/properties" xmlns:x="http://schemas.microsoft.com/winfx/2006/xaml" xmlns:sys="clr-namespace:System;assembly=mscorlib">
  <Rule.Categories>
    <Category Name="General" DisplayName="General" />
    <Category Name="Optimization" DisplayName="Optimization" />
    <Category Name="Preprocessor" DisplayName="Preprocessor" />
    <Category Name="Code Generation" DisplayName="Code Generation" />
    <Category Name="Language" DisplayName="Language" />
    <Category Name="Advanced" DisplayName="Advanced" />
    <Category Name="All Options" DisplayName="All Options" Subtype="Search" />
    <Category Name="Command Line" DisplayName="Command Line" Subtype="CommandLine" />
  </Rule.Categories>
  <Rule.DataSource>
    <DataSource Persistence="ProjectFile" ItemType="ClCompile" Label="" HasConfigurationCondition="true" />
  </Rule.DataSource>
  <BoolProperty Name="MSVCErrorReport" DisplayName="Enable Visual Studio Style Error Reporting" Description="Report errors in a format that Visual Studio can parse." Category="General" Switch="fdiagnostics-format=msvc" Visible="false" F1Keyword="">
  </BoolProperty>
  <StringProperty Name="GccToolChain" DisplayName="GCC Toolchain" Description="Folder path to GCC toolchain." Category="General" Switch="gcc-toolchain " Visible="true" F1Keyword="">
  </StringProperty>
  <StringProperty Name="Target" DisplayName="Target" Description="Target" Category="General" Switch="target " Visible="false" F1Keyword="">
  </StringProperty>
  <StringProperty Name="SysRoot" DisplayName="System Root" Description="Folder path to the root directory for headers and libraries." Category="General" Switch="-sysroot=" Visible="true" F1Keyword="">
  </StringProperty>
  <StringListProperty Subtype="folder" Name="AdditionalIncludeDirectories" DisplayName="Additional Include Directories" Description="Specifies a semicolon delimited list of one or more directories to add to the include path. (-I[path])." Category="General" Switch="I " F1Keyword="VC.Project.VCClangCompilerTool.AdditionalIncludeDirectories">
  </StringListProperty>
  <EnumProperty Name="DebugInformationFormat" DisplayName="Debug Information Format" Description="Specifies the type of debugging information generated by the compiler." Category="General" F1Keyword="VC.Project.VCClangCompilerTool.DebugInformationFormat">
    <EnumValue Name="None" Switch="g0" DisplayName="None" Description="Produces no debugging information, so compilation may be faster.">
    </EnumValue>
    <EnumValue Name="Minimal" Switch="g1" DisplayName="Minimal Debug Information" Description="Generate minimal debug information.">
    </EnumValue>
    <EnumValue Name="FullDebug" Switch="g2 -gdwarf-2" DisplayName="Full Debug Information (DWARF2)" Description="Generate DWARF2 debug information.">
    </EnumValue>
  </EnumProperty>
  <StringProperty Subtype="file" Name="ObjectFileName" DisplayName="Object File Name" Description="Specifies a name to override the default object file name; can be file or directory name. (-o [name])." Category="General" Switch="o " F1Keyword="VC.Project.VCClangCompilerTool.ObjectFile">
  </StringProperty>
  <EnumProperty Name="WarningLevel" DisplayName="Warning Level" Description="Select how strict you want the compiler to be about code errors. Other flags should be added directly to Additional Options. (/w, /Weverything)." Category="General" F1Keyword="VC.Project.VCClangCompilerTool.WarningLevel">
    <EnumValue Name="TurnOffAllWarnings" Switch="w" DisplayName="Turn Off All Warnings" Description="Disables all compiler warnings.">
    </EnumValue>
    <EnumValue Name="EnableAllWarnings" Switch="Wall" DisplayName="EnableAllWarnings" Description="Enables all warnings, including those disabled by default.">
    </EnumValue>
  </EnumProperty>
  <BoolProperty Name="TreatWarningAsError" DisplayName="Treat Warnings As Errors" Description="Treats all compiler warnings as errors. For a new project, it may be best to use /Werror in all compilations; resolving all warnings will ensure the fewest possible hard-to-find code defects." Category="General" Switch="Werror" F1Keyword="VC.Project.VCClangCompilerTool.WarnAsError">
  </BoolProperty>
  <StringListProperty Name="CAdditionalWarning" DisplayName="C Additional Warnings" Description="Defines a set of additional warning messages." Category="General" Switch="W" F1Keyword="VC.Project.VCClangCompilerTool.AdditionalWarning" />
  <StringListProperty Name="CppAdditionalWarning" DisplayName="C++ Additional Warnings" Visible="true" Description="Defines a set of additional warning messages." Category="General" Switch="W" F1Keyword="VC.Project.VCClangCompilerTool.AdditionalWarning" />
  <BoolProperty Name="Verbose" DisplayName="Enable Verbose mode" Description="Additional build information is output when verbose mode is enabled." Category="General" Switch="v" F1Keyword="VC.Project.VCClangCompilerTool.Verbose">
  </BoolProperty>
  <StringProperty Subtype="folder" Name="TrackerLogDirectory" DisplayName="Tracker Log Directory" Description="Tracker Log Directory." Category="General" IncludeInCommandLine="false" Visible="false">
  </StringProperty>
  <EnumProperty Name="Optimization" DisplayName="Optimization" Description="Specifies the optimization level for the application." Category="Optimization" F1Keyword="VC.Project.VCClangCompilerTool.Optimization">
    <EnumValue Name="Custom" Switch="" DisplayName="Custom" Description="Custom optimization.">
    </EnumValue>
    <EnumValue Name="Disabled" Switch="O0" DisplayName="Disabled" Description="Disable optimization.">
    </EnumValue>
    <EnumValue Name="MinSize" Switch="Os" DisplayName="Minimize Size" Description="Optimize for size.">
    </EnumValue>
    <EnumValue Name="MaxSpeed" Switch="O2" DisplayName="Maximize Speed" Description="Optimize for speed.">
    </EnumValue>
    <EnumValue Name="Full" Switch="O3" DisplayName="Full Optimization" Description="Expensive optimizations.">
    </EnumValue>
  </EnumProperty>
  <BoolProperty ReverseSwitch="fno-strict-aliasing" Name="StrictAliasing" DisplayName="Strict Aliasing" Description="Assume the strictest aliasing rules. An object of one type will never be assumed to reside at the same address as an object of a different type." Category="Optimization" Switch="fstrict-aliasing" F1Keyword="VC.Project.VCClangCompilerTool.StrictAliasing">
  </BoolProperty>
  <BoolProperty Name="UnrollLoops" DisplayName="Unroll Loops" Description="Unroll loops to make application faster by reducing number of branches executed at the cost of larger code size." Category="Optimization" Switch="funroll-all-loops" F1Keyword="VC.Project.VCClangCompilerTool.UnrollLoops">
  </BoolProperty>
  <BoolProperty Name="LinkTimeOptimization" DisplayName="Link Time Optimization" Description="Enable Inter-Procedural optimizations by allowing the optimizer to look across object files in your application." Category="Optimization" Switch="flto" F1Keyword="VC.Project.VCClangCompilerTool.LinkTimeOptimization">
  </BoolProperty>
  <BoolProperty ReverseSwitch="fno-omit-frame-pointer" Name="OmitFramePointers" DisplayName="Omit Frame Pointer" Description="Suppresses creation of frame pointers on the call stack." Category="Optimization" Switch="fomit-frame-pointer" F1Keyword="VC.Project.VCClangCompilerTool.OmitFramePointers">
  </BoolProperty>
  <BoolProperty Name="NoCommonBlocks" DisplayName="No Common Blocks" Description="Allocate unintialized global variables in the data section of the object file, rather then generating them as common blocks." Category="Optimization" Switch="fno-common" F1Keyword="VC.Project.VCClangCompilerTool.NoCommonBlocks">
  </BoolProperty>
  <EnumProperty Name="EnableAVE" DisplayName="Enable Additional Vector Extensions" Description="Enables the use of extended vector instructions. Only used when targeting Intel architectures." Category="Code Generation" F1Keyword="VC.Project.VCClangCompilerTool.EnableAVE" Visible="ture">
    <EnumValue Name="SSE3" Switch="msse3" DisplayName="SSE3 Instruction Set" Description="Enable SSE3 instruction set.">
    </EnumValue>
    <EnumValue Name="SSE3 (with supplemental extensions)" Switch="mssse3" DisplayName="SSE3 Supplemental Instruction Set" Description="Enable SSE3 instruction set.">
    </EnumValue>
    <EnumValue Name="SSE41" Switch="msse4.1" DisplayName="SSE4.1 Instruction Set" Description="Enable SSE41 instruction set.">
    </EnumValue>
    <EnumValue Name="SSE42" Switch="msse4.2" DisplayName="SSE4.2 Instruction Set" Description="Enable SSE42 instruction set.">
    </EnumValue>
    <EnumValue Name="AVX" Switch="mavx" DisplayName="AVX Instruction Set" Description="Enable AVX instruction set.">
    </EnumValue>
    <EnumValue Name="AVX2" Switch="mavx2" DisplayName="AVX2 Instruction Set" Description="Enable AVX2 instruction set.">
    </EnumValue>
  </EnumProperty>
  <BoolProperty Name="PositionIndependentCode" DisplayName="Position Independent Code" Description="Generate Position Independent Code (PIC) for use in a shared library." Category="Code Generation" Switch="fpic" F1Keyword="VC.Project.VCClangCompilerTool.PIC">
  </BoolProperty>
  <BoolProperty Name="RelaxIEEE" DisplayName="Floating Point Optimization" Description="Enables floating point optimizations by relaxing IEEE-754 compliance." Category="Code Generation" Switch="ffast-math" F1Keyword="VC.Project.VCClangCompilerTool.RelaxIEEE">
  </BoolProperty>
  <BoolProperty Name="HideInlineMethods" DisplayName="Inline Methods Hidden" Description="When enabled, out-of-line copies of inline methods are declared 'private extern'." Category="Code Generation" Switch="fvisibility-inlines-hidden" F1Keyword="VC.Project.VCClangCompilerTool.HideInlineMethods">
  </BoolProperty>
  <BoolProperty Name="SymbolsHiddenByDefault" DisplayName="Symbol Hiddens By Default" Description="All symbols are declared 'private extern' unless explicitly marked to be exported using the '__attribute' macro." Category="Code Generation" Switch="fvisibility=hidden" F1Keyword="VC.Project.VCClangCompilerTool.SymbolsHiddenByDefault">
  </BoolProperty>
  <EnumProperty Name="ExceptionHandling" DisplayName="Enable C++ Exceptions" Visible="true" Description="Specifies the model of exception handling to be used by the compiler." Category="Code Generation" F1Keyword="VC.Project.VCClangCompilerTool.ExceptionHandling">
    <EnumValue Name="Disabled" Switch="fno-exceptions" DisplayName="No" Description="Disable exception handling.">
    </EnumValue>
    <EnumValue Name="Enabled" Switch="fexceptions" DisplayName="Yes" Description="Enable exception handling.">
    </EnumValue>
  </EnumProperty>
  <EnumProperty Name="CLanguageStandard" DisplayName="C Language Standard" Visible="true" Description="Determines the C language standard." Category="Language" F1Keyword="VC.Project.VCClangCompilerTool.CLanguageStandard">
    <EnumValue Name="Default" Switch="" DisplayName="Default">
    </EnumValue>
    <EnumValue Name="c89" Switch="std=c89" DisplayName="C89" Description="C89 Language Standard.">
    </EnumValue>
    <EnumValue Name="c99" Switch="std=c99" DisplayName="C99" Description="C99 Language Standard.">
    </EnumValue>
    <EnumValue Name="c11" Switch="std=c11" DisplayName="C11" Description="C11 Language Standard.">
    </EnumValue>
    <EnumValue Name="gnu99" Switch="std=gnu99" DisplayName="C99 (GNU Dialect)" Description="C99 (GNU Dialect) Language Standard.">
    </EnumValue>
    <EnumValue Name="gnu11" Switch="std=gnu11" DisplayName="C11 (GNU Dialect)" Description="C11 (GNU Dialect) Language Standard.">
    </EnumValue>
  </EnumProperty>
  <EnumProperty Name="CppLanguageStandard" DisplayName="C++ Language Standard" Visible="true" Description="Determines the C++ language standard." Category="Language" F1Keyword="VC.Project.VCClangCompilerTool.CppLanguageStandard">
    <EnumValue Name="Default" Switch="" DisplayName="Default" Description="">
    </EnumValue>
    <EnumValue Name="c++98" Switch="std=c++98" DisplayName="C++03" Description="C++03 Language Standard.">
    </EnumValue>
    <EnumValue Name="c++11" Switch="std=c++11" DisplayName="C++11" Description="C++11 Language Standard.">
    </EnumValue>
    <EnumValue Name="c++1y" Switch="std=c++14" DisplayName="C++14" Description="C++14 Language Standard.">
    </EnumValue>
    <EnumValue Name="gnu++98" Switch="std=gnu++98" DisplayName="C++03 (GNU Dialect)" Description="C++03 (GNU Dialect) Language Standard.">
    </EnumValue>
    <EnumValue Name="gnu++11" Switch="std=gnu++11" DisplayName="C++11 (GNU Dialect)" Description="C++11 (GNU Dialect) Language Standard.">
    </EnumValue>
    <EnumValue Name="gnu++1y" Switch="std=gnu++14" DisplayName="C++14 (GNU Dialect)" Description="C++14 (GNU Dialect) Language Standard.">
    </EnumValue>
  </EnumProperty>
  <StringListProperty Name="PreprocessorDefinitions" DisplayName="Preprocessor Definitions" Description="Defines preprocessing symbols for your source file. (-D)" Category="Preprocessor" Switch="D " F1Keyword="VC.Project.VCClangCompilerTool.PreprocessorDefinitions">
  </StringListProperty>
  <StringListProperty Name="UndefinePreprocessorDefinitions" DisplayName="Undefine Preprocessor Definitions" Description="Specifies one or more preprocessor undefines. (-U [macro])" Category="Preprocessor" Switch="U " F1Keyword="VC.Project.VCClangCompilerTool.UndefinePreprocessorDefinitions">
  </StringListProperty>
  <BoolProperty Name="UndefineAllPreprocessorDefinitions" DisplayName="Undefine All Preprocessor Definitions" Description="Undefine all previously defined preprocessor values. (-undef)" Category="Preprocessor" Switch="undef" F1Keyword="VC.Project.VCClangCompilerTool.UndefineAllPreprocessorDefinitions">
  </BoolProperty>
  <BoolProperty Name="ShowIncludes" DisplayName="Show Includes" Description="Generates a list of include files with compiler output. (-H)" Category="Preprocessor" Switch="H" F1Keyword="VC.Project.VCClangCompilerTool.ShowIncludes">
  </BoolProperty>
  <EnumProperty Name="CompileAs" DisplayName="Compile As" Visible="true" Description="Select compile language option for .c and .cpp files. 'Default' will detect based on .c or .cpp extension. (-x c, -x c++)" Category="Advanced" F1Keyword="VC.Project.VCClangCompilerTool.CompileAs">
    <EnumValue Name="Default" Switch="" DisplayName="Default" Description="Default.">
    </EnumValue>
    <EnumValue Name="CompileAsC" Switch="x c" DisplayName="Compile as C Code" Description="Compile as C Code.">
    </EnumValue>
    <EnumValue Name="CompileAsCpp" Switch="x c++" DisplayName="Compile as C++ Code" Description="Compile as C++ Code.">
    </EnumValue>
  </EnumProperty>
  <StringListProperty Subtype="file" Name="ForcedIncludeFiles" DisplayName="Forced Include Files" Description="Specifies any forced include files. (-include [name])" Category="Advanced" Switch="include " F1Keyword="VC.Project.VCClangCompilerTool.ForcedIncludeFiles">
  </StringListProperty>
  <BoolProperty Name="UseMultiToolTask" DisplayName="Multi-processor Compilation" Description="Multi-processor Compilation." Category="Advanced" F1Keyword="VC.Project.VCClangCompilerTool.MultiProcessorCompilation">
    <BoolProperty.DataSource>
      <DataSource Persistence="ProjectFile" ItemType="" Label="" HasConfigurationCondition="true" />
    </BoolProperty.DataSource>
  </BoolProperty>
  <StringProperty Name="AdditionalOptions" DisplayName="Additional Options" Description="Additional Options." Category="Command Line" F1Keyword="vc.project.AdditionalOptionsPage">
  </StringProperty>
  <BoolProperty Name="BuildingInIde" Visible="false">
  </BoolProperty>
</Rule>